tbt/__init__.py
tbt-1.0.2.dist-info/LICENSE
tbt-1.0.2.dist-info/METADATA
tbt-1.0.2.dist-info/WHEEL
tbt-1.0.2.dist-info/top_level.txt
tbt-1.0.2.dist-info/RECORD
