Metadata-Version: 2.1
Name: tbt
Version: 1.0.2
Summary: Tamis Basic Tools
Home-page: UNKNOWN
Author: Tami
Author-email: tammyshead@tuta.io
License: UNKNOWN
Platform: UNKNOWN
Classifier: Programming Language :: Python :: 3
Classifier: License :: OSI Approved :: MIT License
Classifier: Operating System :: OS Independent
